xmlcanon/__init__.py
xmlcanon/exceptions.py
xmlcanon/transform.py
xmlcanon-1.0.0.dist-info/licenses/LICENSE
xmlcanon-1.0.0.dist-info/METADATA
xmlcanon-1.0.0.dist-info/WHEEL
xmlcanon-1.0.0.dist-info/top_level.txt
xmlcanon-1.0.0.dist-info/RECORD
