Metadata-Version: 2.4
Name: xmlcanon
Version: 1.0.0
Summary: XML Canonicalization для Python
Home-page: https://github.com/imdeniil/xmlcanon
Author: Daniil (imdeniil)
Author-email: "Daniil (imdeniil)" <keemor821@gmail.com>
License: MIT
Project-URL: Homepage, https://github.com/imdeniil/xmlcanon
Project-URL: Repository, https://github.com/imdeniil/xmlcanon
Project-URL: Bug Reports, https://github.com/imdeniil/xmlcanon/issues
Keywords: xml,canonicalization,exc-c14n,xmldsig,gost,signature
Classifier: Development Status :: 4 - Beta
Classifier: Intended Audience :: Developers
Classifier: Topic :: Software Development :: Libraries :: Python Modules
Classifier: Topic :: Text Processing :: Markup :: XML
Classifier: Topic :: Security :: Cryptography
Classifier: License :: OSI Approved :: MIT License
Classifier: Programming Language :: Python :: 3
Classifier: Programming Language :: Python :: 3.6
Classifier: Programming Language :: Python :: 3.7
Classifier: Programming Language :: Python :: 3.8
Classifier: Programming Language :: Python :: 3.9
Classifier: Programming Language :: Python :: 3.10
Classifier: Programming Language :: Python :: 3.11
Classifier: Programming Language :: Python :: 3.12
Classifier: Operating System :: OS Independent
Requires-Python: >=3.6
License-File: LICENSE
Provides-Extra: lxml
Requires-Dist: lxml>=4.0.0; extra == "lxml"
Provides-Extra: dev
Requires-Dist: pytest>=6.0; extra == "dev"
Requires-Dist: pytest-cov; extra == "dev"
Requires-Dist: black; extra == "dev"
Requires-Dist: flake8; extra == "dev"
Requires-Dist: mypy; extra == "dev"
Provides-Extra: docs
Requires-Dist: sphinx; extra == "docs"
Requires-Dist: sphinx-rtd-theme; extra == "docs"
Dynamic: author
Dynamic: home-page
Dynamic: license-file
Dynamic: requires-python
